{
	"name": "pl_create_trip_data_green",
	"properties": {
		"activities": [
			{
				"name": "getFolderList",
				"type": "Script",
				"dependsOn": [],
				"policy": {
					"timeout": "0.12:00:00",
					"retry": 0,
					"retryIntervalInSeconds": 30,
					"secureOutput": false,
					"secureInput": false
				},
				"userProperties": [],
				"linkedServiceName": {
					"referenceName": "ls_nyc_taxi_ldw",
					"type": "LinkedServiceReference"
				},
				"typeProperties": {
					"scripts": [
						{
							"type": "Query",
							"text": "use nyc_taxi_ldw;\nselect distinct year,month from bronze.vw_trip_data_green;"
						}
					],
					"scriptBlockExecutionTimeout": "02:00:00"
				}
			},
			{
				"name": "ForEachPartition",
				"description": "For each year and month partition data",
				"type": "ForEach",
				"dependsOn": [
					{
						"activity": "getFolderList",
						"dependencyConditions": [
							"Succeeded"
						]
					}
				],
				"userProperties": [],
				"typeProperties": {
					"items": {
						"value": "@activity('getFolderList').output.resultSets[0].rows",
						"type": "Expression"
					},
					"activities": [
						{
							"name": "Delete Partitions",
							"type": "Delete",
							"dependsOn": [],
							"policy": {
								"timeout": "0.12:00:00",
								"retry": 0,
								"retryIntervalInSeconds": 30,
								"secureOutput": false,
								"secureInput": false
							},
							"userProperties": [],
							"typeProperties": {
								"dataset": {
									"referenceName": "ds_nyc_taxi_data",
									"type": "DatasetReference",
									"parameters": {
										"folderPath": {
											"value": "@concat('raw/silver/trip_data_green/year=',item().year,'/month=',item().month)",
											"type": "Expression"
										}
									}
								},
								"enableLogging": false,
								"storeSettings": {
									"type": "AzureBlobFSReadSettings",
									"recursive": true,
									"enablePartitionDiscovery": false
								}
							}
						},
						{
							"name": "create silver partitions",
							"type": "SqlServerStoredProcedure",
							"dependsOn": [
								{
									"activity": "Delete Partitions",
									"dependencyConditions": [
										"Succeeded"
									]
								}
							],
							"policy": {
								"timeout": "0.12:00:00",
								"retry": 0,
								"retryIntervalInSeconds": 30,
								"secureOutput": false,
								"secureInput": false
							},
							"userProperties": [],
							"typeProperties": {
								"storedProcedureName": "[silver].[usp_silver_trip_data_green]",
								"storedProcedureParameters": {
									"month": {
										"value": {
											"value": "@item().month",
											"type": "Expression"
										},
										"type": "String"
									},
									"year": {
										"value": {
											"value": "@item().year",
											"type": "Expression"
										},
										"type": "String"
									}
								}
							},
							"linkedServiceName": {
								"referenceName": "ls_nyc_taxi_ldw",
								"type": "LinkedServiceReference"
							}
						}
					]
				}
			}
		],
		"variables": {
			"folderList": {
				"type": "Array"
			},
			"folders": {
				"type": "Array"
			}
		},
		"folder": {
			"name": "DWH"
		},
		"annotations": []
	}
}